iptcinfo3.py
IPTCInfo3Plus-2.1.5.dist-info/METADATA
IPTCInfo3Plus-2.1.5.dist-info/WHEEL
IPTCInfo3Plus-2.1.5.dist-info/top_level.txt
IPTCInfo3Plus-2.1.5.dist-info/RECORD
