Metadata-Version: 2.2
Name: IPTCInfo3Plus
Version: 2.1.5
Summary: Fork of IPTCInfo3, a Python module for extracting IPTC metadata from images.
Home-page: https://github.com/jamesacampbell/iptcinfo3
Download-URL: https://github.com/jamesacampbell/iptcinfo3
Author: Sanyam Khurana
Author-email: sanyam@sanyamkhurana.com
Maintainer: Sanyam Khurana
Maintainer-email: sanyam@sanyamkhurana.com
License: http://www.opensource.org/licenses/gpl-license.php
Platform: any
Classifier: Development Status :: 3 - Alpha
Classifier: License :: OSI Approved :: Artistic License
Classifier: License :: OSI Approved :: GNU General Public License (GPL)
Classifier: Intended Audience :: Developers
Classifier: Programming Language :: Python
Classifier: Topic :: Multimedia :: Graphics
Classifier: Topic :: Utilities
Dynamic: author
Dynamic: author-email
Dynamic: classifier
Dynamic: description
Dynamic: download-url
Dynamic: home-page
Dynamic: license
Dynamic: maintainer
Dynamic: maintainer-email
Dynamic: platform
Dynamic: summary
